{
  "comments": [
    {
      "videoid": 1,
      "password": "1111",
      "text": "테스트1",
      "id": 1
    },
    {
      "videoid": 1,
      "password": "2222",
      "text": "테스트2",
      "id": 2
    },
    {
      "videoid": 1,
      "password": "3333",
      "text": "테스트3",
      "id": 3
    },
    {
      "videoid": 1,
      "password": "4444",
      "text": "테스트4",
      "id": 4
    },
    {
      "videoid": 1,
      "password": "5555",
      "text": "테스트5",
      "id": 5
    },
    {
      "videoid": 1,
      "password": "6666",
      "text": "테스트6",
      "id": 6
    },
    {
      "videoid": 1,
      "password": "7777",
      "text": "테스트7",
      "id": 7
    },
    {
      "videoid": 1,
      "password": "8888",
      "text": "테스트8",
      "id": 8
    },
    {
      "videoid": 1,
      "password": "9999",
      "text": "테스트9",
      "id": 9
    }
  ],
  "youtubetwo": [],
  "youtubethree": [],
  "youtubeone": [
    [
      {
        "kind": "youtube#searchResult",
        "etag": "Fdavu9dxQUZyIQMMicvv2SKTf9s",
        "id": {
          "kind": "youtube#channel",
          "channelId": "UCC9pQY_uaBSa0WOpMNJHbEQ"
        },
        "snippet": {
          "publishedAt": "2019-03-20T07:34:47Z",
          "channelId": "UCC9pQY_uaBSa0WOpMNJHbEQ",
          "title": "자취요리신 simple cooking",
          "description": "요리를 모르는 분들도 누구나 할 수 있도록 쉽고 간단하고 빠르게 요리를 알려드립니다. 문의 - simcook@sandbox.co.kr.",
          "thumbnails": {
            "default": {
              "url": "https://yt3.ggpht.com/lNaYuezkRiTzKQ4WNaxO0e0ciRTxEn0HXG47fJs1Iv333ETGiktBxxbWdOXKVh0fuljM88gGGQ=s88-c-k-c0xffffffff-no-rj-mo"
            },
            "medium": {
              "url": "https://yt3.ggpht.com/lNaYuezkRiTzKQ4WNaxO0e0ciRTxEn0HXG47fJs1Iv333ETGiktBxxbWdOXKVh0fuljM88gGGQ=s240-c-k-c0xffffffff-no-rj-mo"
            },
            "high": {
              "url": "https://yt3.ggpht.com/lNaYuezkRiTzKQ4WNaxO0e0ciRTxEn0HXG47fJs1Iv333ETGiktBxxbWdOXKVh0fuljM88gGGQ=s800-c-k-c0xffffffff-no-rj-mo"
            }
          },
          "channelTitle": "자취요리신 simple cooking",
          "liveBroadcastContent": "none",
          "publishTime": "2019-03-20T07:34:47Z"
        }
      }
    ],
    [
      [
        {
          "kind": "youtube#searchResult",
          "etag": "Fdavu9dxQUZyIQMMicvv2SKTf9s",
          "id": {
            "kind": "youtube#channel",
            "channelId": "UCC9pQY_uaBSa0WOpMNJHbEQ"
          },
          "snippet": {
            "publishedAt": "2019-03-20T07:34:47Z",
            "channelId": "UCC9pQY_uaBSa0WOpMNJHbEQ",
            "title": "자취요리신 simple cooking",
            "description": "요리를 모르는 분들도 누구나 할 수 있도록 쉽고 간단하고 빠르게 요리를 알려드립니다. 문의 - simcook@sandbox.co.kr.",
            "thumbnails": {
              "default": {
                "url": "https://yt3.ggpht.com/lNaYuezkRiTzKQ4WNaxO0e0ciRTxEn0HXG47fJs1Iv333ETGiktBxxbWdOXKVh0fuljM88gGGQ=s88-c-k-c0xffffffff-no-rj-mo"
              },
              "medium": {
                "url": "https://yt3.ggpht.com/lNaYuezkRiTzKQ4WNaxO0e0ciRTxEn0HXG47fJs1Iv333ETGiktBxxbWdOXKVh0fuljM88gGGQ=s240-c-k-c0xffffffff-no-rj-mo"
              },
              "high": {
                "url": "https://yt3.ggpht.com/lNaYuezkRiTzKQ4WNaxO0e0ciRTxEn0HXG47fJs1Iv333ETGiktBxxbWdOXKVh0fuljM88gGGQ=s800-c-k-c0xffffffff-no-rj-mo"
              }
            },
            "channelTitle": "자취요리신 simple cooking",
            "liveBroadcastContent": "none",
            "publishTime": "2019-03-20T07:34:47Z"
          }
        }
      ]
    ],
    [
      [
        {
          "kind": "youtube#searchResult",
          "etag": "Fdavu9dxQUZyIQMMicvv2SKTf9s",
          "id": {
            "kind": "youtube#channel",
            "channelId": "UCC9pQY_uaBSa0WOpMNJHbEQ"
          },
          "snippet": {
            "publishedAt": "2019-03-20T07:34:47Z",
            "channelId": "UCC9pQY_uaBSa0WOpMNJHbEQ",
            "title": "자취요리신 simple cooking",
            "description": "요리를 모르는 분들도 누구나 할 수 있도록 쉽고 간단하고 빠르게 요리를 알려드립니다. 문의 - simcook@sandbox.co.kr.",
            "thumbnails": {
              "default": {
                "url": "https://yt3.ggpht.com/lNaYuezkRiTzKQ4WNaxO0e0ciRTxEn0HXG47fJs1Iv333ETGiktBxxbWdOXKVh0fuljM88gGGQ=s88-c-k-c0xffffffff-no-rj-mo"
              },
              "medium": {
                "url": "https://yt3.ggpht.com/lNaYuezkRiTzKQ4WNaxO0e0ciRTxEn0HXG47fJs1Iv333ETGiktBxxbWdOXKVh0fuljM88gGGQ=s240-c-k-c0xffffffff-no-rj-mo"
              },
              "high": {
                "url": "https://yt3.ggpht.com/lNaYuezkRiTzKQ4WNaxO0e0ciRTxEn0HXG47fJs1Iv333ETGiktBxxbWdOXKVh0fuljM88gGGQ=s800-c-k-c0xffffffff-no-rj-mo"
              }
            },
            "channelTitle": "자취요리신 simple cooking",
            "liveBroadcastContent": "none",
            "publishTime": "2019-03-20T07:34:47Z"
          }
        }
      ]
    ]
  ]
}
