{
  "comments": [
    {
      "videoId": "2",
      "password": "2222",
      "text": "테스트2",
      "id": 1
    },
    {
      "videoId": "1",
      "password": "1111",
      "text": "테스트1",
      "id": 2
    },
    {
      "videoId": "3",
      "password": "3333",
      "text": "테스트3",
      "id": 3
    },
    {
      "videoId": "4",
      "password": "4444",
      "text": "테스트4",
      "id": 4
    },
    {
      "videoId": "2",
      "password": "2222",
      "text": "테스트2",
      "id": 5
    },
    {
      "videoId": "2",
      "password": "2222",
      "text": "테스트2\n\n",
      "id": 6
    },
    {
      "videoId": "2",
      "password": "2222",
      "text": "테스트2\n\n",
      "id": 7
    },
    {
      "videoId": "2",
      "password": "2222",
      "text": "테스트2\n\n",
      "id": 8
    },
    {
      "videoId": "1",
      "password": "1111",
      "text": "테스트1",
      "id": 9
    },
    {
      "videoId": "pdqs3exO5Aw",
      "password": "0000",
      "text": "진미채볶음",
      "id": 10
    },
    {
      "videoId": "o0Si6EnLH8A",
      "password": "0000",
      "text": "꿀팁",
      "id": 11
    },
    {
      "videoId": "syPd_QwGM5c",
      "password": "1111",
      "text": "ddddd3333",
      "id": 12
    },
    {
      "videoId": "M46HRw1iZfk",
      "password": "2222",
      "text": "안녕하세요",
      "id": 13
    },
    {
      "videoId": "M46HRw1iZfk",
      "password": "1111",
      "text": "ㅇㅇㅇㅇ",
      "id": 14
    },
    {
      "videoId": "rEnnfMFAijU",
      "password": "1111",
      "text": "맛있겠다!!!!",
      "id": 15
    },
    {
      "videoId": "abuh1ccnHHY",
      "password": "1111",
      "text": "감사합니다~!!!",
      "id": 16
    }
  ]
}